README.md
setup.py
saltedpwd/__init__.py
saltedpwd/functions.py
saltedpwd/test_salted.py
saltedpwd.egg-info/PKG-INFO
saltedpwd.egg-info/SOURCES.txt
saltedpwd.egg-info/dependency_links.txt
saltedpwd.egg-info/entry_points.txt
saltedpwd.egg-info/not-zip-safe
saltedpwd.egg-info/requires.txt
saltedpwd.egg-info/top_level.txt