Metadata-Version: 1.0
Name: saltedpwd
Version: 0.0.3
Summary: Generate safe password with random salt
Home-page: https://github.com/ipconfiger/saltedpwd
Author: Alexander.Li
Author-email: superpowerlee@gmail.com
License: GNU GENERAL PUBLIC LICENSE3.0
Platform: UNKNOWN
